{
    "id": "qga",
    "name": "Queens Gambit Accepted",
    "positions": {
      "1": "rnbqkbnr/pppppppp/8/8/3P4/8/PPP1PPPP/RNBQKBNR",
      "2": "rnbqkbnr/ppp1pppp/8/3p4/3P4/8/PPP1PPPP/RNBQKBNR",
      "3": "rnbqkbnr/ppp1pppp/8/3p4/2PP4/8/PP2PPPP/RNBQKBNR",
      "4": "rnbqkbnr/ppp1pppp/8/8/2pP4/8/PP2PPPP/RNBQKBNR",
      "5": "rnbqkbnr/ppp1pppp/8/8/2pPP3/8/PP3PPP/RNBQKBNR",
      "6": "rnbqkbnr/ppp2ppp/8/4p3/2pPP3/8/PP3PPP/RNBQKBNR"
    },
    "moves": {
      "1": "d4",
      "2": "d5",
      "3": "c4",
      "4": "dxc4",
      "5": "e4",
      "6": "e5"
    },
    "info": {
    "1": "White takes the center with the pawn",
    "2": "Black matches with the pawn",
    "3": "White performs the gambit and allows a take on the c4 pawn",
    "4": "Black accepts the gambit and now we are in the queens gambit accepted",
    "5": "White pushes the E2 pawn to take the center",
    "6": "Black matches the white pawn push"
    },
    "moveLength": "6"
  }